openstack_voms_auth_type/__init__.py
openstack_voms_auth_type/utils.py
openstack_voms_auth_type/v2.py
openstack_voms_auth_type/v3.py
openstack_voms_auth_type-3.0.1.dist-info/AUTHORS
openstack_voms_auth_type-3.0.1.dist-info/METADATA
openstack_voms_auth_type-3.0.1.dist-info/WHEEL
openstack_voms_auth_type-3.0.1.dist-info/entry_points.txt
openstack_voms_auth_type-3.0.1.dist-info/pbr.json
openstack_voms_auth_type-3.0.1.dist-info/top_level.txt
openstack_voms_auth_type-3.0.1.dist-info/RECORD
