Metadata-Version: 2.1
Name: openstack-voms-auth-type
Version: 3.0.1
Summary: VOMS-based authentication for OpenStack
Home-page: https://github.com/EGI-Foundation/openstack-voms-auth-type
Author: Enol Fernandez
Author-email: enol.fernandez@egi.eu
License: UNKNOWN
Project-URL: Code, https://github.com/EGI-Foundation/openstack-voms-auth-type
Project-URL: Issue tracker, https://github.com/EGI-Foundation/openstack-voms-auth-type/issues
Project-URL: Documentation, https://egi-federated-cloud.readthedocs.io/en/latest/
Platform: UNKNOWN
Classifier: Environment :: OpenStack
Classifier: Intended Audience :: Information Technology
Classifier: Intended Audience :: System Administrators
Classifier: License :: OSI Approved :: Apache Software License
Classifier: Operating System :: POSIX :: Linux
Classifier: Programming Language :: Python
Classifier: Programming Language :: Python :: 2
Classifier: Programming Language :: Python :: 2.7
Classifier: Programming Language :: Python :: 3
Classifier: Programming Language :: Python :: 3.4
Classifier: Programming Language :: Python :: 3.5
Requires-Dist: pbr (>=1.6)
Requires-Dist: keystoneauth1 (>=2.10.0)
Requires-Dist: osc-lib (>=1.2.0)
Requires-Dist: python-openstackclient (>=3.0)
Requires-Dist: positional
